Workbook

Sheet Raw_Data
A1: Record_ID | B1: Statement | C1: Category | D1: Account | E1: Amount | F1: Period_Start | G1: Period_End | H1: As_Of_Date | I1: Is_Total | J1: Sort_Order
A2: 1 | B2: Income Statement | C2: Revenue | D2: Gross Revenue | E2: 15580941 | F2: 45292 | G2: 45657 | I2: =FALSE() -> FALSE | J2: 1
A3: 2 | B3: Income Statement | C3: Revenue | D3: Less: Sales Returns | E3: -1437905 | F3: 45292 | G3: 45657 | I3: =FALSE() -> FALSE | J3: 2
A4: 3 | B4: Income Statement | C4: Revenue | D4: Net Revenue | E4: 14143036 | F4: 45292 | G4: 45657 | I4: =FALSE() -> FALSE | J4: 3
A5: 4 | B5: Income Statement | C5: Cost of Sales | D5: Cost of Goods Sold (COGS) | E5: -11117500 | F5: 45292 | G5: 45657 | I5: =FALSE() -> FALSE | J5: 4
A6: 5 | B6: Income Statement | C6: Gross Profit | D6: Gross Profit | E6: 3025536 | F6: 45292 | G6: 45657 | I6: =TRUE() -> TRUE | J6: 5
A7: 6 | B7: Income Statement | C7: Operating Expenses | D7: Salaries and Wages Expense | E7: -1573726 | F7: 45292 | G7: 45657 | I7: =FALSE() -> FALSE | J7: 6
A8: 7 | B8: Income Statement | C8: Operating Expenses | D8: Facility Rental Expense | E8: -235350 | F8: 45292 | G8: 45657 | I8: =FALSE() -> FALSE | J8: 7
A9: 8 | B9: Income Statement | C9: Operating Expenses | D9: Marketing Expense | E9: -568200 | F9: 45292 | G9: 45657 | I9: =FALSE() -> FALSE | J9: 8
A10: 9 | B10: Income Statement | C10: Operating Expenses | D10: Utilities and Other Expenses | E10: -21150 | F10: 45292 | G10: 45657 | I10: =FALSE() -> FALSE | J10: 9
A11: 10 | B11: Income Statement | C11: Operating Expenses | D11: Depreciation Expense | E11: -15000 | F11: 45292 | G11: 45657 | I11: =FALSE() -> FALSE | J11: 10
A12: 11 | B12: Income Statement | C12: Operating Expenses | D12: Total Operating Expenses | E12: -2413426 | F12: 45292 | G12: 45657 | I12: =TRUE() -> TRUE | J12: 11
A13: 12 | B13: Income Statement | C13: Operating Profit | D13: Operating Profit | E13: 612110 | F13: 45292 | G13: 45657 | I13: =TRUE() -> TRUE | J13: 12
A14: 13 | B14: Income Statement | C14: Finance Costs | D14: Interest Expense | E14: -75536 | F14: 45292 | G14: 45657 | I14: =FALSE() -> FALSE | J14: 13
A15: 14 | B15: Income Statement | C15: Profit Before Tax | D15: Profit Before Tax | E15: 536574 | F15: 45292 | G15: 45657 | I15: =TRUE() -> TRUE | J15: 14
A16: 15 | B16: Income Statement | C16: Income Tax | D16: Income Tax Expense | E16: -25000 | F16: 45292 | G16: 45657 | I16: =FALSE() -> FALSE | J16: 15
A17: 16 | B17: Income Statement | C17: Net Profit | D17: Net Profit | E17: 511574 | F17: 45292 | G17: 45657 | I17: =TRUE() -> TRUE | J17: 16
A18: 17 | B18: Statement of Changes in Equity | C18: Equity | D18: Beginning Capital (January 1, 2024) | E18: 8308426 | F18: 45292 | G18: 45657 | H18: 45657 | I18: =FALSE() -> FALSE | J18: 17
A19: 18 | B19: Statement of Changes in Equity | C19: Equity | D19: Add: Net Profit for the Current Year | E19: 511574 | F19: 45292 | G19: 45657 | H19: 45657 | I19: =FALSE() -> FALSE | J19: 18
A20: 19 | B20: Statement of Changes in Equity | C20: Equity | D20: Less: Owner's Withdrawals (Drawings) | E20: -20000 | F20: 45292 | G20: 45657 | H20: 45657 | I20: =FALSE() -> FALSE | J20: 19
A21: 20 | B21: Statement of Changes in Equity | C21: Equity | D21: Ending Capital (December 31, 2024) | E21: 8800000 | F21: 45292 | G21: 45657 | H21: 45657 | I21: =TRUE() -> TRUE | J21: 20
A22: 21 | B22: Statement of Financial Position | C22: Current Assets | D22: Cash and Cash Equivalents | E22: 3450000 | H22: 45657 | I22: =FALSE() -> FALSE | J22: 21
A23: 22 | B23: Statement of Financial Position | C23: Current Assets | D23: Accounts Receivable | E23: 1250000 | H23: 45657 | I23: =FALSE() -> FALSE | J23: 22
A24: 23 | B24: Statement of Financial Position | C24: Current Assets | D24: Inventory | E24: 4500000 | H24: 45657 | I24: =FALSE() -> FALSE | J24: 23
A25: 24 | B25: Statement of Financial Position | C25: Current Assets | D25: Total Current Assets | E25: 9200000 | H25: 45657 | I25: =TRUE() -> TRUE | J25: 24
A26: 25 | B26: Statement of Financial Position | C26: Fixed Assets | D26: Store Buildings | E26: 15000000 | H26: 45657 | I26: =FALSE() -> FALSE | J26: 25
A27: 26 | B27: Statement of Financial Position | C27: Fixed Assets | D27: Equipment and Computers | E27: 2500000 | H27: 45657 | I27: =FALSE() -> FALSE | J27: 26
A28: 27 | B28: Statement of Financial Position | C28: Fixed Assets | D28: Accumulated Depreciation | E28: -500000 | H28: 45657 | I28: =FALSE() -> FALSE | J28: 27
A29: 28 | B29: Statement of Financial Position | C29: Fixed Assets | D29: Total Fixed Assets | E29: 17000000 | H29: 45657 | I29: =TRUE() -> TRUE | J29: 28
A30: 29 | B30: Statement of Financial Position | C30: Assets | D30: Total Assets | E30: 26200000 | H30: 45657 | I30: =TRUE() -> TRUE | J30: 29
A31: 30 | B31: Statement of Financial Position | C31: Current Liabilities | D31: Accounts Payable | E31: 1150000 | H31: 45657 | I31: =FALSE() -> FALSE | J31: 30
A32: 31 | B32: Statement of Financial Position | C32: Current Liabilities | D32: Taxes Payable | E32: 250000 | H32: 45657 | I32: =FALSE() -> FALSE | J32: 31
A33: 32 | B33: Statement of Financial Position | C33: Current Liabilities | D33: Total Current Liabilities | E33: 1400000 | H33: 45657 | I33: =TRUE() -> TRUE | J33: 32
A34: 33 | B34: Statement of Financial Position | C34: Non-current Liabilities | D34: Bank Loan (Expansion Financing) | E34: 16000000 | H34: 45657 | I34: =FALSE() -> FALSE | J34: 33
A35: 34 | B35: Statement of Financial Position | C35: Non-current Liabilities | D35: Total Non-current Liabilities | E35: 16000000 | H35: 45657 | I35: =TRUE() -> TRUE | J35: 34
A36: 35 | B36: Statement of Financial Position | C36: Equity | D36: Ending Capital | E36: 8800000 | H36: 45657 | I36: =FALSE() -> FALSE | J36: 35
A37: 36 | B37: Statement of Financial Position | C37: Liabilities and Equity | D37: Total Liabilities and Equity | E37: 26200000 | H37: 45657 | I37: =TRUE() -> TRUE | J37: 36

Sheet Financial_Analysis
A1: Financial Analysis
A3: Income Statement Metrics
A5: Metric | B5: Source Account | C5: Amount | D5: Notes
A6: Gross Revenue | B6: Gross Revenue | C6: =IFERROR(SUMIFS(Raw_Data!$E$2:$E$37,Raw_Data!$D$2:$D$37,Financial_Analysis!B6),0) -> 15580941 | D6: Direct from statement
A7: Sales Returns | B7: Less: Sales Returns | C7: =IFERROR(SUMIFS(Raw_Data!$E$2:$E$37,Raw_Data!$D$2:$D$37,Financial_Analysis!B7),0) -> -1437905 | D7: Shown as positive deduction
A8: Net Revenue | B8: Net Revenue | C8: =IFERROR(SUMIFS(Raw_Data!$E$2:$E$37,Raw_Data!$D$2:$D$37,Financial_Analysis!B8),0) -> 14143036 | D8: Direct from statement
A9: COGS | B9: Cost of Goods Sold (COGS) | C9: =IFERROR(SUMIFS(Raw_Data!$E$2:$E$37,Raw_Data!$D$2:$D$37,Financial_Analysis!B9),0) -> -11117500 | D9: Shown as positive cost
A10: Gross Profit | B10: Gross Profit | C10: =IFERROR(SUMIFS(Raw_Data!$E$2:$E$37,Raw_Data!$D$2:$D$37,Financial_Analysis!B10),0) -> 3025536 | D10: Direct from statement
A11: Operating Expenses | B11: Total Operating Expenses | C11: =IFERROR(SUMIFS(Raw_Data!$E$2:$E$37,Raw_Data!$D$2:$D$37,Financial_Analysis!B11),0) -> -2413426 | D11: Shown as positive expense
A12: Operating Profit | B12: Operating Profit | C12: =IFERROR(SUMIFS(Raw_Data!$E$2:$E$37,Raw_Data!$D$2:$D$37,Financial_Analysis!B12),0) -> 612110 | D12: Direct from statement
A13: Interest Expense | B13: Interest Expense | C13: =IFERROR(SUMIFS(Raw_Data!$E$2:$E$37,Raw_Data!$D$2:$D$37,Financial_Analysis!B13),0) -> -75536 | D13: Shown as positive expense
A14: Profit Before Tax | B14: Profit Before Tax | C14: =IFERROR(SUMIFS(Raw_Data!$E$2:$E$37,Raw_Data!$D$2:$D$37,Financial_Analysis!B14),0) -> 536574 | D14: Direct from statement
A15: Income Tax Expense | B15: Income Tax Expense | C15: =IFERROR(SUMIFS(Raw_Data!$E$2:$E$37,Raw_Data!$D$2:$D$37,Financial_Analysis!B15),0) -> -25000 | D15: Shown as positive expense
A16: Net Profit | B16: Net Profit | C16: =IFERROR(SUMIFS(Raw_Data!$E$2:$E$37,Raw_Data!$D$2:$D$37,Financial_Analysis!B16),0) -> 511574 | D16: Direct from statement
A19: KPI Ratios
A21: KPI | B21: Formula Basis | C21: Result | D21: Interpretation
A22: Revenue Growth | B22: Previous year not available in statement | C22: 0 | D22: Statement contains only FY2024, so growth is not calculated
A23: Gross Profit Margin | B23: Gross Profit / Net Revenue | C23: =IFERROR(C10/C8,0) -> 0.21392408 | D23: Profit retained after COGS
A24: Operating Profit Margin | B24: Operating Profit / Net Revenue | C24: =IFERROR(C12/C8,0) -> 0.043279958 | D24: Operating profit per EGP of net revenue
A25: Net Profit Margin | B25: Net Profit / Net Revenue | C25: =IFERROR(C16/C8,0) -> 0.036171442 | D25: Net profit per EGP of net revenue
A26: Expense to Revenue Ratio | B26: Operating Expenses / Net Revenue | C26: =IFERROR(C11/C8,0) -> -0.17064412 | D26: Operating expense burden relative to revenue
A29: Statement of Financial Position (As of 31-Dec-2024)
A31: Metric | B31: Source Account | C31: Amount | D31: Notes
A32: Total Assets | B32: Total Assets | C32: =IFERROR(SUMIFS(Raw_Data!$E$2:$E$37,Raw_Data!$D$2:$D$37,Financial_Analysis!B32),0) -> 26200000 | D32: As-of balance sheet amount
A33: Total Liabilities | B33: Total Current Liabilities | C33: =IFERROR(SUMIFS(Raw_Data!$E$2:$E$37,Raw_Data!$D$2:$D$37,Financial_Analysis!B33),0) -> 1400000 | D33: As-of balance sheet amount
A34: Total Liabilities and Equity | B34: Total Liabilities and Equity | C34: =IFERROR(SUMIFS(Raw_Data!$E$2:$E$37,Raw_Data!$D$2:$D$37,Financial_Analysis!B34),0) -> 26200000 | D34: As-of balance sheet amount
A35: Equity | B35: Ending Capital | C35: =IFERROR(SUMIFS(Raw_Data!$E$2:$E$37,Raw_Data!$D$2:$D$37,Financial_Analysis!B35),0) -> 8800000 | D35: As-of balance sheet amount

Sheet Dashboard_Data
A1: Metric | B1: Amount (EGP) | D1: Profit Metric | E1: Amount (EGP)
A2: Net Revenue | B2: =Financial_Analysis!C8 -> 14143036 | D2: Gross Profit | E2: =Financial_Analysis!C10 -> 3025536
A3: COGS | B3: =Financial_Analysis!C9 -> -11117500 | D3: Operating Profit | E3: =Financial_Analysis!C12 -> 612110
A4: Operating Expenses | B4: =Financial_Analysis!C11 -> -2413426 | D4: Net Profit | E4: =Financial_Analysis!C16 -> 511574
A5: Interest Expense | B5: =Financial_Analysis!C13 -> -75536
A6: Income Tax Expense | B6: =Financial_Analysis!C15 -> -25000

Sheet Dashboard
B2: Financial Reporting Dashboard
B4: Report Year | C4: 2024
B6: Total Revenue | E6: Total Expenses | H6: Gross Profit | K6: Net Profit
B7: =Financial_Analysis!C8 -> 14143036 | E7: =Financial_Analysis!C11 -> -2413426 | H7: =Financial_Analysis!C10 -> 3025536 | K7: =Financial_Analysis!C16 -> 511574
B10: Net Profit Margin | E10: Gross Profit Margin | H10: Operating Profit Margin | K10: Total Assets
B11: =Financial_Analysis!C25 -> 0.036171442 | E11: =Financial_Analysis!C23 -> 0.21392408 | H11: =Financial_Analysis!C24 -> 0.043279958 | K11: =Financial_Analysis!C32 -> 26200000
