Workbook
Name valuevx: 42.314159

Sheet Ledger
B2: Cash | G2: 1.1
B3: Date | C3: Description | D3: Debit | E3: Credit | F3: Balance
F4: Debit | G4: Credit
B5: 46184 | C5: Opening Balance | D5: 20117100 | F5: 20117100
B6: 46184 | C6: Operating Expenses | E6: 420000 | F6: 19697100
B7: 46185 | C7: Operating Expenses | E7: 100000 | F7: 19597100
B8: 46188 | C8: Operating Expenses | E8: 780000 | F8: 18817100
B9: 46189 | C9: Operating Expenses | E9: 100000 | F9: 18717100
B10: 46189 | C10: Donation for the Prayer Room | E10: 186000 | F10: 18531100
B11: 46190 | C11: Operating Expenses | E11: 100000 | F11: 18431100
B12: 46191 | C12: Operating Expenses | E12: 350000 | F12: 18081100
B13: 46192 | C13: Operating Expenses | E13: 50000 | F13: 18031100
B14: 46192 | C14: Salary Expense | E14: 650000 | F14: 17381100
B15: 46193 | C15: Operating Expenses | E15: 100000 | F15: 17281100
B16: 46195 | C16: Operating Expenses | E16: 580000 | F16: 16701100
B17: 46196 | C17: Operating Expenses | E17: 100000 | F17: 16601100
... B20: 46198 | C20: Operating Expenses | E20: 420000 | F20: 15877100
B21: 46198 | C21: Revenue from VG | D21: 84000 | F21: 15961100
B22: 46200 | C22: Operating Expenses | E22: 100000 | F22: 15861100
B23: 46202 | C23: Operating Expenses | E23: 530000 | F23: 15331100
B24: 46202 | C24: Revenue from VG | D24: 265000 | F24: 15596100
B25: 46202 | C25: Revenue from VG | D25: 200000 | F25: 15796100
B26: 46204 | C26: Operating Expenses | E26: 150000 | F26: 15646100
B27: 46205 | C27: Operating Expenses | E27: 440000 | F27: 15206100
B28: 46206 | C28: Operating Expenses | E28: 200000 | F28: 15006100
B29: 46206 | C29: Revenue from GA | D29: 2145000 | F29: 17151100
B30: 46209 | C30: Operating Expenses | E30: 650000 | F30: 16501100
B31: 46209 | C31: Consumption Expense | E31: 35000 | F31: 16466100
B32: 46211 | C32: Operating Expenses | E32: 100000 | F32: 16366100
B33: 46211 | C33: Revenue from KA | D33: 1804000 | F33: 18170100
B34: 46211 | C34: Consumption Expense | E34: 15000 | F34: 18155100
B35: 46212 | C35: Operating Expenses | E35: 350000 | F35: 17805100
B36: 46212 | C36: Revenue from GPT | D36: 650000 | F36: 18455100
B37: 46213 | C37: Operating Expenses | E37: 200000 | F37: 18255100
B38: 46213 | C38: Driver's Salary Expense | E38: 700000 | F38: 17555100
B39: 46213 | C39: Assistant 1 Salary Expense | E39: 700000 | F39: 16855100
B40: 46213 | C40: Assistant 2 Salary Expense | E40: 700000 | F40: 16155100
B41: 46213 | C41: Revenue from PAP 1 | D41: 936000 | F41: 17091100
B42: 46213 | C42: Revenue from MP | D42: 3015000 | F42: 20106100
B44: Account Receivable | G44: 1.2
B45: Date | C45: Description | D45: Debit | E45: Credit | F45: Balance
F46: Debit | G46: Credit
B47: 46184 | C47: Opening Balance | D47: 2962000 | F47: =D47 -> 2962000
B48: 46204 | C48: GA Receivable | D48: 468000 | F48: =F47+D48-E48 -> 3430000
B49: 46204 | C49: GA Payment | E49: 36000 | F49: =F48+D49-E49 -> 3394000
B50: 46206 | C50: GA Receivable | D50: 216000 | F50: =F49+D50-E50 -> 3610000
B51: 46206 | C51: GA Payment | E51: 234000 | F51: =F50+D51-E51 -> 3376000
B52: 46213 | C52: KV Receivable | D52: 1920000 | F52: =F51+D52-E52 -> 5296000
B54: Allowance for Uncollectible Accounts | G54: 1.3
B55: Date | C55: Description | D55: Debit | E55: Credit | F55: Balance
F56: Debit | G56: Credit
B57: 46123 | F57: =D57 -> 0
B59: Office | G59: 1.5
B60: Date | C60: Description | D60: Debit | E60: Credit | F60: Balance
F61: Debit | G61: Credit
B62: 45870 | C62: Office | D62: 1000000000 | F62: =D62 -> 1000000000
B64: Vehicle - Dump Truck | G64: 1.6
B65: Date | C65: Description | D65: Debit | E65: Credit | F65: Balance
F66: Debit | G66: Credit
B67: 45870 | C67: Vehicle - Dump Truck | D67: 150000000 | F67: =D67 -> 150000000
B69: Accumulated Depreciation – Vehicles – Dump Truck | G69: 1.6.1
B70: Date | C70: Description | D70: Debit | E70: Credit | F70: Balance
F71: Debit | G71: Credit
B72: 46122 | C72: Depreciation Adjustment | E72: 10937500 | G72: =E72 -> 10937500
B74: Vehicle - L300 | G74: 1.7
B75: Date | C75: Description | D75: Debit | E75: Credit | F75: Balance
F76: Debit | G76: Credit
B77: 45870 | C77: Vehicle - L300 | D77: 90000000 | F77: =D77 -> 90000000
B79: Accumulated Depreciation – Vehicles – L300 | G79: 1.7.1
B80: Date | C80: Description | D80: Debit | E80: Credit | F80: Balance
F81: Debit | G81: Credit
B82: 46183 | C82: Depreciation Adjustment | E82: 8437500 | G82: =E82 -> 8437500
B83: 46213 | C83: Depreciation Adjustment | E83: 937500 | G83: =G82+E83 -> 9375000
B85: Capital | G85: 3.1
B86: Date | C86: Description | D86: Debit | E86: Credit | F86: Balance
F87: Debit | G87: Credit
B88: 46183 | C88: Opening Balance | E88: 1211965000 | G88: =E88 -> 1211965000
B89: 46183 | C89: Owner's Drawings | D89: 230000 | G89: =G88-D89 -> 1211735000
B91: Retained Earning | G91: 3.2
B92: Date | C92: Description | D92: Debit | E92: Credit | F92: Balance
F93: Debit | G93: Credit
B94: 46183 | C94: Retained Earnings, June 10, 2026 | E94: 31969100 | G94: =E94 -> 31969100
B97: Owner's Drawings | G97: 3.3
B98: Date | C98: Description | D98: Debit | E98: Credit | F98: Balance
F99: Debit | G99: Credit
F100: =D100 -> 0
F101: =F100+D101 -> 0
B103: Revenue | G103: 4.1
B104: Date | C104: Description | D104: Debit | E104: Credit | F104: Balance
F105: Debit | G105: Credit
B106: 46198 | C106: Revenue from VG | E106: 84000 | G106: =E106 -> 84000
B107: 46202 | C107: Revenue from VG | E107: 265000 | G107: =G106-D107+E107 -> 349000
B108: 46202 | C108: Revenue from VG | E108: 200000 | G108: =G107-D108+E108 -> 549000
B109: 46206 | C109: Revenue from GA | E109: =2145000+ 414000 -> 2559000 | G109: =G108-D109+E109 -> 3108000
B110: 46211 | C110: Revenue from KA | E110: 1804000 | G110: =G109-D110+E110 -> 4912000
B111: 46212 | C111: Revenue from GPT | E111: 650000 | G111: =G110-D111+E111 -> 5562000
B112: 46213 | C112: Revenue from PAP 1 | E112: 936000 | G112: =G111-D112+E112 -> 6498000
B113: 46213 | C113: Revenue from MP | E113: 3015000 | G113: =G112-D113+E113 -> 9513000
B114: 46213 | C114: Revenue from KV | E114: 1920000 | G114: =G113-D114+E114 -> 11433000
B116: Fuel Expense | G116: 5.1
...

Sheet Trial Balance
B2: Account No | C2: Journal | D2: Debit | E2: Credit
B3: 1.1 | C3: Cash | D3: =Ledger!F42 -> 20106100
B4: 1.2 | C4: Account Receivable | D4: =Ledger!F52 -> 5296000
B5: 1.3 | C5: Allowance for Uncollectible Accounts | D5: =Ledger!F57 -> 0
B6: 1.5 | C6: Office | D6: =Ledger!F62 -> 1000000000
B7: 1.6 | C7: Vehicle - Dump Truck | D7: =Ledger!F67 -> 150000000
B8: 1.6.1 | C8: Accumulated Depreciation – Vehicles – Dump Truck | E8: =Ledger!G72 -> 10937500
B9: 1.7 | C9: Vehicle - L300 | D9: =Ledger!F77 -> 90000000
B10: 1.7.1 | C10: Accumulated Depreciation – Vehicles – L300 | E10: =Ledger!G83 -> 9375000
B11: 3.1 | C11: Capital | E11: =Ledger!G89 -> 1211735000
B12: 3.2 | C12: Retained Earning | E12: =Ledger!G94 -> 31969100
B13: 3.3 | C13: Owner's Drawings | D13: =Ledger!F101 -> 0
B14: 4.1 | C14: Revenue | E14: =Ledger!G114 -> 11433000
B15: 5.1 | C15: Fuel Expense | D15: =Ledger!F127 -> 2800000
B16: 5.2 | C16: Meal Allowance Expense | D16: =Ledger!F138 -> 1320000
B17: 5.3 | C17: Levy Expense | D17: =Ledger!F163 -> 2000000
B18: 5.4 | C18: Maintenance Expense | D18: =Ledger!F170 -> 0
B19: 5.5 | C19: Fee Expense | D19: =Ledger!F175 -> 186000
B20: 5.6 | C20: Depreciation Expense | D20: =Ledger!F180 -> 937500
B21: 5.7 | C21: Salary Expense | D21: =Ledger!F188 -> 2750000
B22: 5.8 | C22: Consumption Expenses and Others | D22: =Ledger!F195 -> 54000
B23: 5.9 | C23: Bad Debt Expense | D23: =Ledger!F200 -> 0
B24: Total | D24: =SUM(D3:D23) -> 1275449600 | E24: =SUM(E3:E23) -> 1275449600
D26: =D24-E24 -> 0

Sheet Income Statement
B1: PT MPM | E1: Income Statement
E2: FOR THE PERIOD ENDED JULY 10, 2026
B4: Revenue | D4: JULY 2026 | E4: JUNE 2026
C5: Revenue | D5: ='Trial Balance'!E14 -> 11433000 | E5: 11350000
B6: Total Revenue | D6: =D5 -> 11433000 | E6: =E5 -> 11350000
E7: [42]
A8: [42] | B8: Operating Expenses
C9: Fuel Expense | D9: ='Trial Balance'!D15 -> 2800000 | E9: 2920000
C10: Meal Allowance Expense | D10: ='Trial Balance'!D16 -> 1320000 | E10: 1800000
C11: Levy Expense | D11: ='Trial Balance'!D17 -> 2000000 | E11: 2750000
C12: Maintenance Expense | D12: ='Trial Balance'!D18 -> 0 | E12: 1680000
C13: Fee Expense | D13: ='Trial Balance'!D19 -> 186000 | E13: 1043000
C14: Depreciation Expense | D14: ='Trial Balance'!D20 -> 937500 | E14: 937500
C15: Salary Expense | D15: ='Trial Balance'!D21 -> 2750000 | E15: 4550000
C16: Refreshment and Miscellaneous Expenses | D16: ='Trial Balance'!D22 -> 54000 | E16: 398000
C17: Bad Debt Expense | D17: ='Trial Balance'!D23 -> 0 | E17: 0
B18: Total Operating Expenses | D18: =SUM(D9:D17) -> 10047500 | E18: =SUM(E9:E17) -> 16078500
B20: Laba Bersih | D20: =D6-D18 -> 1385500 | E20: =E6-E18 -> -4728500

Sheet Statement of Changes in Equity
B1: PT MPM | E1: Statement of Changes in Equity
E2: Period Ended July 10, 2026
B4: Description | D4: JULY 2026 | E4: JUNE 2026
C5: Capital | D5: ='Trial Balance'!E11 -> 1211735000 | E5: 1211965000
C6: Retained Earnings | D6: ='Trial Balance'!E12 -> 31969100 | E6: 36697600
C7: Net Profit (Loss) | D7: ='Income Statement'!D20 -> 1385500 | E7: -4728500
C8: Personal | D8: =-'Trial Balance'!D13 -> 0 | E8: -230000
B9: Total Equity | D9: =SUM(D5:D8) -> 1245089600 | E9: =SUM(E5:E8) -> 1243704100

Sheet Balance Sheet
B1: PT MPM | E1: Balance Sheet
E2: AS OF JULY 10, 2026
B4: Assets | D4: JULY 2026 | E4: JUNE 2026
B5: Current Assets
C6: Cash | D6: ='Trial Balance'!D3 -> 20106100 | E6: 20117100
C7: Accounts Receivable | D7: ='Trial Balance'!D4 -> 5296000 | E7: 2962000
C8: Allowance for Doubtful Accounts | D8: ='Trial Balance'!D5 -> 0 | E8: 0
C9: Total Current Assets | D9: =SUM(D6:D8) -> 25402100 | E9: =SUM(E6:E8) -> 23079100
B10: Fixed Assets
C11: Office | D11: ='Trial Balance'!D6 -> 1000000000 | E11: 1000000000
C12: Vehicles - Dump Truck | D12: ='Trial Balance'!D7 -> 150000000 | E12: 150000000
C13: Vehicles - L300 | D13: ='Trial Balance'!D9 -> 90000000 | E13: 90000000
C14: Accumulated Depreciation - Dump Truck | D14: =-'Trial Balance'!E8 -> -10937500 | E14: -10937500
C15: Accumulated Depreciation - L300 | D15: =-'Trial Balance'!E10 -> -9375000 | E15: -8437500
C16: Total Fixed Assets | D16: =SUM(D11:D15) -> 1219687500 | E16: =SUM(E11:E15) -> 1220625000
B17: Total Assets | D17: =D9+D16 -> 1245089600 | E17: =E9+E16 -> 1243704100
A19: [42] | B19: Liabilities and Equity
B20: Current Liabilities
C22: Total Current Liabilities | E22: 0
B23: Long-term Debt
C25: Total Long-term Debt | E25: 0
B26: Equity
C27: Capital | D27: ='Trial Balance'!E11 -> 1211735000 | E27: 1211965000
C28: Retained Earnings | D28: ='Trial Balance'!E12 -> 31969100 | E28: 36697600
C29: Retained Earnings | D29: ='Income Statement'!D20 -> 1385500 | E29: -4728500
C30: Personal | D30: ='Statement of Changes in Equity'!D8 -> 0 | E30: -230000
C31: Total Equity | D31: =SUM(D27:D30) -> 1245089600 | E31: =SUM(E27:E30) -> 1243704100
B33: Total Liabilities and Equity | D33: =D31+D25+D22 -> 1245089600 | E33: =E31+E25+E22 -> 1243704100
E34: {42}
B35: Common Financial Ratios
B36: Debt Ratio (Total Liabilities / Total Assets) | D36: 0.55888185
B37: Current Ratio (Current Assets / Current Liabilities) | D37: 1.0597055
B38: Working Capital (Current Assets - Current Liabilities) | D38: 669 | E38: 0
B39: Assets-to-Equity Ratio (Total Assets / Owner's Equity) | D39: 2.2669664
B40: Debt-to-Equity Ratio (Total Liabilities / Owner's Equity) | D40: 1.2669664

Sheet Statement of Cash Flows
B1: PT MPM
B2: Statement of Cash Flows
F4: PERIOD OF JULY 10, 2026
B6: Date | C6: Description | D6: Debit | E6: Credit | F6: Balance
B7: 46184 | C7: Opening Balance | D7: 20117100 | F7: =D7 -> 20117100
B8: 46184 | C8: Operating Expenses | E8: 420000 | F8: =F7+D8-E8 -> 19697100
B9: 46185 | C9: Operating Expenses | E9: 100000 | F9: =F8+D9-E9 -> 19597100
B10: 46188 | C10: Operating Expenses | E10: 780000 | F10: =F9+D10-E10 -> 18817100
B11: 46189 | C11: Operating Expenses | E11: 100000 | F11: =F10+D11-E11 -> 18717100
B12: 46189 | C12: Donation for the Prayer Room | E12: 186000 | F12: =F11+D12-E12 -> 18531100
B13: 46190 | C13: Operating Expenses | E13: 100000 | F13: =F12+D13-E13 -> 18431100
B14: 46191 | C14: Operating Expenses | E14: 350000 | F14: =F13+D14-E14 -> 18081100
B15: 46192 | C15: Operating Expenses | E15: 50000 | F15: =F14+D15-E15 -> 18031100
B16: 46192 | C16: Salary Expense | E16: 650000 | F16: =F15+D16-E16 -> 17381100
B17: 46193 | C17: Operating Expenses | E17: 100000 | F17: =F16+D17-E17 -> 17281100
B18: 46195 | C18: Operating Expenses | E18: 580000 | F18: =F17+D18-E18 -> 16701100
B19: 46196 | C19: Operating Expenses | E19: 100000 | F19: =F18+D19-E19 -> 16601100
... B22: 46198 | C22: Operating Expenses | E22: 420000 | F22: =F21+D22-E22 -> 15877100
B23: 46198 | C23: Revenue from VG | D23: 84000 | F23: =F22+D23-E23 -> 15961100
B24: 46200 | C24: Operating Expenses | E24: 100000 | F24: =F23+D24-E24 -> 15861100
B25: 46202 | C25: Operating Expenses | E25: 530000 | F25: =F24+D25-E25 -> 15331100
B26: 46202 | C26: Revenue from VG | D26: 265000 | F26: =F25+D26-E26 -> 15596100
B27: 46202 | C27: Revenue from VG | D27: 200000 | F27: =F26+D27-E27 -> 15796100
B28: 46204 | C28: Operating Expenses | E28: 150000 | F28: =F27+D28-E28 -> 15646100
B29: 46205 | C29: Operating Expenses | E29: 440000 | F29: =F28+D29-E29 -> 15206100
B30: 46206 | C30: Operating Expenses | E30: 200000 | F30: =F29+D30-E30 -> 15006100
B31: 46206 | C31: Revenue from GA | D31: 2145000 | F31: =F30+D31-E31 -> 17151100
B32: 46209 | C32: Operating Expenses | E32: 650000 | F32: =F31+D32-E32 -> 16501100
B33: 46209 | C33: Consumption Expense | E33: 35000 | F33: =F32+D33-E33 -> 16466100
B34: 46211 | C34: Operating Expenses | E34: 100000 | F34: =F33+D34-E34 -> 16366100
B35: 46211 | C35: Revenue from KA | D35: 1804000 | F35: =F34+D35-E35 -> 18170100
B36: 46211 | C36: Consumption Expense | E36: 15000 | F36: =F35+D36-E36 -> 18155100
B37: 46212 | C37: Operating Expenses | E37: 350000 | F37: =F36+D37-E37 -> 17805100
B38: 46212 | C38: Revenue from GPT | D38: 650000 | F38: =F37+D38-E38 -> 18455100
B39: 46213 | C39: Operating Expenses | E39: 200000 | F39: =F38+D39-E39 -> 18255100
B40: 46213 | C40: Driver's Salary Expense | E40: 700000 | F40: =F39+D40-E40 -> 17555100
B41: 46213 | C41: Assistant 1 Salary Expense | E41: 700000 | F41: =F40+D41-E41 -> 16855100
B42: 46213 | C42: Assistant 2 Salary Expense | E42: 700000 | F42: =F41+D42-E42 -> 16155100
B43: 46213 | C43: Revenue from PAP 1 | D43: 936000 | F43: =F42+D43-E43 -> 17091100
B44: 46213 | C44: Revenue from MP | D44: 3015000 | F44: =F43+D44-E44 -> 20106100
B45: Ending Cash Balance | D45: =SUM(D7:D44) -> 29216100 | E45: =SUM(E7:E44) -> 9110000 | F45: =D45-E45 -> 20106100
